anybodycanai/__init__.py
anybodycanai/core.py
anybodycanai-0.0.1.dist-info/licenses/LICENSE
anybodycanai-0.0.1.dist-info/METADATA
anybodycanai-0.0.1.dist-info/WHEEL
anybodycanai-0.0.1.dist-info/top_level.txt
anybodycanai-0.0.1.dist-info/RECORD
