Metadata-Version: 2.4
Name: anybodycanai
Version: 0.0.1
Summary: Building resources to help folks learn and implement AI
Author-email: Jenil Soni <anybodycanai@gmail.com>
License: MIT
License-File: LICENSE
Dynamic: license-file
